examples/__init__.py
examples/get_listens.py
examples/get_playing_now.py
examples/submit_listens.py
examples/submit_playing_now.py
pylistenbrainz/__init__.py
pylistenbrainz/client.py
pylistenbrainz/errors.py
pylistenbrainz/listen.py
pylistenbrainz/user_artist_stat_response.py
pylistenbrainz/user_recording_stat.py
pylistenbrainz/utils.py
pylistenbrainz/tests/__init__.py
pylistenbrainz/tests/test_client.py
pylistenbrainz-0.5.1.dist-info/LICENSE
pylistenbrainz-0.5.1.dist-info/METADATA
pylistenbrainz-0.5.1.dist-info/WHEEL
pylistenbrainz-0.5.1.dist-info/top_level.txt
pylistenbrainz-0.5.1.dist-info/RECORD
