Metadata-Version: 2.1
Name: pylistenbrainz
Version: 0.5.1
Summary: A simple ListenBrainz client library for Python
Home-page: https://github.com/paramsingh/pylistenbrainz
Author: Param Singh
Author-email: iliekcomputers@gmail.com
License: UNKNOWN
Platform: UNKNOWN
Classifier: Programming Language :: Python :: 3
Classifier: License :: OSI Approved :: GNU General Public License v3 (GPLv3)
Classifier: Operating System :: OS Independent
Requires-Python: >=3.5
Requires-Dist: requests (>=2.23.0)
